FLightcase/__init__.py
FLightcase/__main__.py
FLightcase/client.py
FLightcase/server.py
FLightcase/templates/FL_plan.json
FLightcase/templates/__init__.py
FLightcase/templates/architecture.py
FLightcase/templates/client_node_settings.json
FLightcase/templates/fl-client.service
FLightcase/templates/server_node_settings.json
FLightcase/utils/__init__.py
FLightcase/utils/communication.py
FLightcase/utils/results.py
FLightcase/utils/tracking.py
FLightcase/utils/deep_learning/__init__.py
FLightcase/utils/deep_learning/data.py
FLightcase/utils/deep_learning/evaluation.py
FLightcase/utils/deep_learning/general.py
FLightcase/utils/deep_learning/model.py
FLightcase/utils/deep_learning/train.py
FLightcase/utils/toolbox_manuscript/__init__.py
FLightcase/utils/toolbox_manuscript/centralised_loss_figure.py
FLightcase/utils/toolbox_manuscript/create_loss_figure.py
FLightcase/utils/toolbox_manuscript/describe_data.py
FLightcase/utils/toolbox_manuscript/preprocess_Wood_statedict.py
FLightcase/utils/toolbox_manuscript/pretty_true_pred_test_scatterplot.py
FLightcase/utils/toolbox_manuscript/training_centralised.py
flightcase-0.1.11.dist-info/licenses/LICENSE
flightcase-0.1.11.dist-info/METADATA
flightcase-0.1.11.dist-info/WHEEL
flightcase-0.1.11.dist-info/entry_points.txt
flightcase-0.1.11.dist-info/top_level.txt
flightcase-0.1.11.dist-info/RECORD
